typipe-0.1.2.dist-info/METADATA
typipe-0.1.2.dist-info/WHEEL
typipe-0.1.2.dist-info/licenses/LICENSE
typipe/__init__.py
typipe/typipe.py
typipe-0.1.2.dist-info/RECORD
