Metadata-Version: 2.1
Name: typipe
Version: 0.1.2
Summary: Typed pipe to pipe input into functions.
Author-Email: clvnkhr <calvin_khor@hotmail.com>
License: MIT
Requires-Python: >=3.12
Requires-Dist: attrs>=23.2.0
